Metadata-Version: 2.1
Name: ibm-container-registry
Version: 1.1.0
Summary: IBM Cloud Container Registry Python SDK
Home-page: https://github.com/IBM/container-registry-python-sdk
Author: IBM
Author-email: alchemy.registry.squad@uk.ibm.com
License: Apache 2.0
Keywords: ibm_container_registry
Classifier: Programming Language :: Python
Classifier: Programming Language :: Python :: 3
Classifier: Programming Language :: Python :: 3.7
Classifier: Programming Language :: Python :: 3.8
Classifier: Programming Language :: Python :: 3.9
Classifier: Development Status :: 4 - Beta
Classifier: Intended Audience :: Developers
Classifier: License :: OSI Approved :: Apache Software License
Classifier: Operating System :: OS Independent
Classifier: Topic :: Software Development :: Libraries :: Python Modules
Classifier: Topic :: Software Development :: Libraries :: Application Frameworks
License-File: LICENSE
